{
  "users": [
    {
      "id": "1",
      "username": "user_name-is-abhinav",
      "email": "abhinav@bahikhata.org",
      "password": "Abhinav@12"
    },
    {
      "id": "2",
      "username": "user_name-is-abhinav",
      "email": "email",
      "password": "password"
    },
    {
      "id": "3",
      "username": "user_name-is-abhinav",
      "email": "agarwalabhinav91@gmail.com",
      "password": "password"
    },
    {
      "id": "114f",
      "username": "user_name-is-abhinav",
      "email": "abhinav@bahikhata.org1",
      "password": "Abhinav@00"
    },
    {
      "id": "aa09",
      "username": "user_name-is-abhinav",
      "email": "abhinav@bahikhata.org12",
      "password": "Abhinav@00"
    },
    {
      "id": "3552",
      "username": "user_name-is-abhinav",
      "email": "abhinav@bahikhata.org10",
      "password": "Abhinav@00"
    },
    {
      "id": "2d35e2f0-2707-44c4-9892-de72d41903c1",
      "email": "abhinav@bahikhata.org",
      "username": "noname",
      "password": "Abhinav@12"
    },
    {
      "id": "713c921a-7f72-4ac8-9493-0192f1fbf203",
      "email": "abhinav@bahikhata.org",
      "username": "noname",
      "password": "Abhinav@00"
    },
    {
      "id": "569c5f16-ed74-4e6d-9957-662eace030f4",
      "email": "abhinav00@bahikhata.org",
      "username": "noname",
      "password": "Abhinav@1211"
    }
  ],
  "forms": [],
  "todos": [
    {
      "id": "3",
      "userEmail": "abhinav@bahikhata.org2",
      "text": "The Todo Text is here 3",
      "image": "",
      "isCompleted": false
    },
    {
      "id": "4",
      "userEmail": "abhinav@bahikhata.org",
      "text": "The Todo Text is here 4",
      "image": "",
      "isCompleted": false
    },
    {
      "id": "5",
      "userEmail": "abhinav@bahikhata.org",
      "text": "The Todo Text is here 5",
      "image": "",
      "isCompleted": false
    },
    {
      "id": "9f7da07f-479a-4021-9f36-04e6bd7fbf33",
      "userEmail": "abhinav@bahikhata.org",
      "text": "hello",
      "image": "",
      "isCompleted": false
    },
    {
      "id": "51bc2f50-161f-11f0-a41e-ab7e05ef82c7",
      "userEmail": "abhinav@bahikhata.org",
      "text": "hello",
      "image": "",
      "isCompleted": false
    },
    {
      "id": "1017dad1-cbbd-4db8-884d-5066985fca8e",
      "userEmail": "hello@test.in",
      "text": "hello",
      "image": "",
      "isCompleted": false
    },
    {
      "id": "03014147",
      "userEmail": "abhinav@bahikhata.org",
      "text": "hellllllooooooooooooooooooooooooooo",
      "image": "",
      "isCompleted": false
    },
    {
      "id": "88b7987c-d39a-40bb-b025-9d7f9efb7fa1",
      "userEmail": "hello123@test.in12",
      "text": "Hello World! Mic test",
      "image": "",
      "isCompleted": false
    }
  ]
}